danielssupergameforwinners/__init__.py
danielssupergameforwinners/__main__.py
danielssupergameforwinners/danielssupergameforwinners.py
danielssupergameforwinners/images/WinstonFace.png
danielssupergameforwinners/images/WinstonForGame.png
danielssupergameforwinners/images/WinstonSquare.png
danielssupergameforwinners/images/__init__.py
danielssupergameforwinners-0.1.13.dist-info/LICENSE
danielssupergameforwinners-0.1.13.dist-info/METADATA
danielssupergameforwinners-0.1.13.dist-info/WHEEL
danielssupergameforwinners-0.1.13.dist-info/top_level.txt
danielssupergameforwinners-0.1.13.dist-info/RECORD
