Metadata-Version: 2.1
Name: danielssupergameforwinners
Version: 0.1.13
Summary: The most hype game ever
Author-email: Daniel Hutchings <thewakemaster@gmail.com>
Classifier: Programming Language :: Python :: 3
Classifier: License :: OSI Approved :: MIT License
Classifier: Operating System :: OS Independent
Requires-Python: >=3.8
License-File: LICENSE
